WhatColorIsX.py
WhatColorIsX-1.0.1.dist-info/DESCRIPTION.rst
WhatColorIsX-1.0.1.dist-info/METADATA
WhatColorIsX-1.0.1.dist-info/RECORD
WhatColorIsX-1.0.1.dist-info/WHEEL
WhatColorIsX-1.0.1.dist-info/entry_points.txt
WhatColorIsX-1.0.1.dist-info/metadata.json
WhatColorIsX-1.0.1.dist-info/top_level.txt
