Metadata-Version: 2.0
Name: WhatColorIsX
Version: 1.0.1
Summary: Get color of a string via Google image search API
Home-page: https://github.com/tommilligan/WhatColorIsX
Author: Tom Milligan
Author-email: code@tommilligan.net
License: GPL
Keywords: colour color google image text search find get string
Platform: UNKNOWN
Classifier: Development Status :: 5 - Production/Stable
Classifier: Intended Audience :: Developers
Classifier: Operating System :: OS Independent
Classifier: Topic :: Software Development :: Libraries :: Python Modules
Classifier: License :: OSI Approved :: GNU General Public License v2 (GPLv2)
Classifier: Natural Language :: English
Classifier: Programming Language :: Python :: 3.3
Classifier: Programming Language :: Python :: 3.4
Classifier: Programming Language :: Python :: 3.5
Requires-Dist: Pillow
Requires-Dist: colour
